e_invoice_api/__init__.py
e_invoice_api/_base_client.py
e_invoice_api/_client.py
e_invoice_api/_compat.py
e_invoice_api/_constants.py
e_invoice_api/_exceptions.py
e_invoice_api/_files.py
e_invoice_api/_models.py
e_invoice_api/_qs.py
e_invoice_api/_resource.py
e_invoice_api/_response.py
e_invoice_api/_streaming.py
e_invoice_api/_types.py
e_invoice_api/_version.py
e_invoice_api/pagination.py
e_invoice_api/py.typed
e_invoice_api/_utils/__init__.py
e_invoice_api/_utils/_compat.py
e_invoice_api/_utils/_datetime_parse.py
e_invoice_api/_utils/_json.py
e_invoice_api/_utils/_logs.py
e_invoice_api/_utils/_proxy.py
e_invoice_api/_utils/_reflection.py
e_invoice_api/_utils/_resources_proxy.py
e_invoice_api/_utils/_streams.py
e_invoice_api/_utils/_sync.py
e_invoice_api/_utils/_transform.py
e_invoice_api/_utils/_typing.py
e_invoice_api/_utils/_utils.py
e_invoice_api/lib/.keep
e_invoice_api/resources/__init__.py
e_invoice_api/resources/inbox.py
e_invoice_api/resources/lookup.py
e_invoice_api/resources/me.py
e_invoice_api/resources/outbox.py
e_invoice_api/resources/validate.py
e_invoice_api/resources/webhooks.py
e_invoice_api/resources/documents/__init__.py
e_invoice_api/resources/documents/attachments.py
e_invoice_api/resources/documents/documents.py
e_invoice_api/resources/documents/ubl.py
e_invoice_api/types/__init__.py
e_invoice_api/types/allowance.py
e_invoice_api/types/certificate.py
e_invoice_api/types/charge.py
e_invoice_api/types/currency_code.py
e_invoice_api/types/document_attachment_create.py
e_invoice_api/types/document_attachment_create_param.py
e_invoice_api/types/document_create_from_pdf_params.py
e_invoice_api/types/document_create_from_pdf_response.py
e_invoice_api/types/document_create_params.py
e_invoice_api/types/document_delete_response.py
e_invoice_api/types/document_direction.py
e_invoice_api/types/document_response.py
e_invoice_api/types/document_send_params.py
e_invoice_api/types/document_state.py
e_invoice_api/types/document_type.py
e_invoice_api-1.24.0.dist-info/METADATA
e_invoice_api-1.24.0.dist-info/WHEEL
e_invoice_api-1.24.0.dist-info/licenses/LICENSE
e_invoice_api-1.24.0.dist-info/RECORD
